anon_comp_core/__init__.py
anon_comp_core/anonymization.py
specific/Libraries/__init__.py
specific/Libraries/anonymization_transformations.py
nnanoncomp-0.5.7.dist-info/METADATA
nnanoncomp-0.5.7.dist-info/WHEEL
nnanoncomp-0.5.7.dist-info/top_level.txt
nnanoncomp-0.5.7.dist-info/RECORD
