Metadata-Version: 2.1
Name: nnanoncomp
Version: 0.5.7
Summary: basic wheel for NN anonymization component
Home-page: UNKNOWN
License: UNKNOWN
Platform: UNKNOWN
